observer_config_json/__init__.py
observer_config_json/cli.py
observer_config_json-0.1.5.dist-info/LICENSE
observer_config_json-0.1.5.dist-info/METADATA
observer_config_json-0.1.5.dist-info/WHEEL
observer_config_json-0.1.5.dist-info/top_level.txt
observer_config_json-0.1.5.dist-info/RECORD
